{"meta":{"name":"UK | Betting-BBC Sports","id":"Vipre20","type":"channel","posterShape":"landscape","videos":[{"id":"Viprestream_20_0","title":"UK: Betfred TV"},{"id":"Viprestream_20_1","title":"UK: Coral TV"},{"id":"Viprestream_20_2","title":"UK: Coral TV 2"},{"id":"Viprestream_20_3","title":"UK: Ladbrokes TV 1"},{"id":"Viprestream_20_4","title":"Ladbrokes TV3"},{"id":"Viprestream_20_5","title":"Paddy Power TV 1"},{"id":"Viprestream_20_6","title":"Paddy Power TV2"},{"id":"Viprestream_20_7","title":"Paddy Power TV 3"},{"id":"Viprestream_20_8","title":"Racing.com"},{"id":"Viprestream_20_9","title":"Racing.com"},{"id":"Viprestream_20_10","title":"TVG Racing"},{"id":"Viprestream_20_11","title":"UK: SIS One"},{"id":"Viprestream_20_12","title":"UK: SIS Two"},{"id":"Viprestream_20_13","title":"UK: SIS Racing"},{"id":"Viprestream_20_14","title":"UK: William Hill TV1"},{"id":"Viprestream_20_15","title":"UK: William Hill TV2"},{"id":"Viprestream_20_16","title":"William Hill back up"},{"id":"Viprestream_20_17","title":"bbc sports 1"},{"id":"Viprestream_20_18","title":"bbc sports 2"},{"id":"Viprestream_20_19","title":"bbc sports 3"},{"id":"Viprestream_20_20","title":"bbc sports 4"},{"id":"Viprestream_20_21","title":"bbc sports 5"},{"id":"Viprestream_20_22","title":"bbc sports 6"},{"id":"Viprestream_20_23","title":"bbc sports 7"},{"id":"Viprestream_20_24","title":"bbc sports 8"},{"id":"Viprestream_20_25","title":"bbc sports 9"}]}}